[
  {"make":"Maruti Suzuki","model":"Swift","variant":"ZXi Plus","body_type":"hatchback","fuel_type":"petrol","transmission":"manual","price_min":649000,"price_max":964000,"mileage_kmpl":24.8,"range_km":null,"seating_capacity":5,"safety_rating":3,"engine_cc":1197,"battery_kwh":null,"power_bhp":80.5,"image_url":"https://images.unsplash.com/photo-1542362567-b07e54358753?auto=format&fit=crop&w=900&q=80"},
  {"make":"Maruti Suzuki","model":"Baleno","variant":"Alpha AMT","body_type":"hatchback","fuel_type":"petrol","transmission":"automatic","price_min":666000,"price_max":988000,"mileage_kmpl":22.9,"range_km":null,"seating_capacity":5,"safety_rating":3,"engine_cc":1197,"battery_kwh":null,"power_bhp":88.5,"image_url":"https://images.unsplash.com/photo-1502877338535-766e1452684a?auto=format&fit=crop&w=900&q=80"},
  {"make":"Maruti Suzuki","model":"WagonR","variant":"ZXi Plus CNG","body_type":"hatchback","fuel_type":"cng","transmission":"manual","price_min":554000,"price_max":738000,"mileage_kmpl":34.1,"range_km":null,"seating_capacity":5,"safety_rating":2,"engine_cc":1197,"battery_kwh":null,"power_bhp":76.4,"image_url":"https://images.unsplash.com/photo-1494976388531-d1058494cdd8?auto=format&fit=crop&w=900&q=80"},
  {"make":"Hyundai","model":"i20","variant":"Asta IVT","body_type":"hatchback","fuel_type":"petrol","transmission":"automatic","price_min":704000,"price_max":1130000,"mileage_kmpl":20.0,"range_km":null,"seating_capacity":5,"safety_rating":3,"engine_cc":1197,"battery_kwh":null,"power_bhp":87,"image_url":"https://images.unsplash.com/photo-1552519507-da3b142c6e3d?auto=format&fit=crop&w=900&q=80"},
  {"make":"Tata","model":"Altroz","variant":"XZA Plus DCA","body_type":"hatchback","fuel_type":"petrol","transmission":"automatic","price_min":665000,"price_max":1065000,"mileage_kmpl":18.5,"range_km":null,"seating_capacity":5,"safety_rating":5,"engine_cc":1199,"battery_kwh":null,"power_bhp":86.8,"image_url":"https://images.unsplash.com/photo-1533473359331-0135ef1b58bf?auto=format&fit=crop&w=900&q=80"},
  {"make":"Tata","model":"Tiago","variant":"XZ Plus CNG","body_type":"hatchback","fuel_type":"cng","transmission":"manual","price_min":565000,"price_max":820000,"mileage_kmpl":26.5,"range_km":null,"seating_capacity":5,"safety_rating":4,"engine_cc":1199,"battery_kwh":null,"power_bhp":72,"image_url":"https://images.unsplash.com/photo-1525609004556-c46c7d6cf023?auto=format&fit=crop&w=900&q=80"},
  {"make":"Honda","model":"Amaze","variant":"VX CVT","body_type":"sedan","fuel_type":"petrol","transmission":"automatic","price_min":720000,"price_max":996000,"mileage_kmpl":18.6,"range_km":null,"seating_capacity":5,"safety_rating":4,"engine_cc":1199,"battery_kwh":null,"power_bhp":88.5,"image_url":"https://images.unsplash.com/photo-1549924231-f129b911e442?auto=format&fit=crop&w=900&q=80"},
  {"make":"Hyundai","model":"Aura","variant":"SX CNG","body_type":"sedan","fuel_type":"cng","transmission":"manual","price_min":648000,"price_max":949000,"mileage_kmpl":28.0,"range_km":null,"seating_capacity":5,"safety_rating":2,"engine_cc":1197,"battery_kwh":null,"power_bhp":68,"image_url":"https://images.unsplash.com/photo-1550355291-bbee04a92027?auto=format&fit=crop&w=900&q=80"},
  {"make":"Maruti Suzuki","model":"Dzire","variant":"ZXi Plus AMT","body_type":"sedan","fuel_type":"petrol","transmission":"automatic","price_min":656000,"price_max":939000,"mileage_kmpl":22.6,"range_km":null,"seating_capacity":5,"safety_rating":2,"engine_cc":1197,"battery_kwh":null,"power_bhp":88.5,"image_url":"https://images.unsplash.com/photo-1503736334956-4c8f8e92946d?auto=format&fit=crop&w=900&q=80"},
  {"make":"Tata","model":"Punch","variant":"Creative AMT","body_type":"suv","fuel_type":"petrol","transmission":"automatic","price_min":613000,"price_max":1040000,"mileage_kmpl":18.8,"range_km":null,"seating_capacity":5,"safety_rating":5,"engine_cc":1199,"battery_kwh":null,"power_bhp":87,"image_url":"https://images.unsplash.com/photo-1519641471654-76ce0107ad1b?auto=format&fit=crop&w=900&q=80"},
  {"make":"Tata","model":"Punch EV","variant":"Empowered Plus LR","body_type":"suv","fuel_type":"electric","transmission":"automatic","price_min":1099000,"price_max":1449000,"mileage_kmpl":null,"range_km":421,"seating_capacity":5,"safety_rating":5,"engine_cc":null,"battery_kwh":35,"power_bhp":120,"image_url":"https://images.unsplash.com/photo-1619767886558-efdc259cde1a?auto=format&fit=crop&w=900&q=80"},
  {"make":"Tata","model":"Nexon","variant":"Fearless Plus DCA","body_type":"suv","fuel_type":"petrol","transmission":"automatic","price_min":800000,"price_max":1510000,"mileage_kmpl":17.4,"range_km":null,"seating_capacity":5,"safety_rating":5,"engine_cc":1199,"battery_kwh":null,"power_bhp":118,"image_url":"https://images.unsplash.com/photo-1533106418989-88406c7cc8ca?auto=format&fit=crop&w=900&q=80"},
  {"make":"Tata","model":"Nexon EV","variant":"Empowered Plus LR","body_type":"suv","fuel_type":"electric","transmission":"automatic","price_min":1249000,"price_max":1699000,"mileage_kmpl":null,"range_km":465,"seating_capacity":5,"safety_rating":5,"engine_cc":null,"battery_kwh":40.5,"power_bhp":143,"image_url":"https://images.unsplash.com/photo-1593941707882-a5bba14938c7?auto=format&fit=crop&w=900&q=80"},
  {"make":"Hyundai","model":"Venue","variant":"SX(O) DCT","body_type":"suv","fuel_type":"petrol","transmission":"automatic","price_min":794000,"price_max":1348000,"mileage_kmpl":18.3,"range_km":null,"seating_capacity":5,"safety_rating":3,"engine_cc":998,"battery_kwh":null,"power_bhp":118,"image_url":"https://images.unsplash.com/photo-1553440569-bcc63803a83d?auto=format&fit=crop&w=900&q=80"},
  {"make":"Kia","model":"Sonet","variant":"GTX Plus DCT","body_type":"suv","fuel_type":"petrol","transmission":"automatic","price_min":799000,"price_max":1550000,"mileage_kmpl":18.2,"range_km":null,"seating_capacity":5,"safety_rating":3,"engine_cc":998,"battery_kwh":null,"power_bhp":118,"image_url":"https://images.unsplash.com/photo-1532581140115-3e355d1ed1de?auto=format&fit=crop&w=900&q=80"},
  {"make":"Maruti Suzuki","model":"Brezza","variant":"ZXi Plus AT","body_type":"suv","fuel_type":"petrol","transmission":"automatic","price_min":834000,"price_max":1400000,"mileage_kmpl":19.8,"range_km":null,"seating_capacity":5,"safety_rating":4,"engine_cc":1462,"battery_kwh":null,"power_bhp":102,"image_url":"https://images.unsplash.com/photo-1541899481282-d53bffe3c35d?auto=format&fit=crop&w=900&q=80"},
  {"make":"Mahindra","model":"XUV 3XO","variant":"AX7L TGDi AT","body_type":"suv","fuel_type":"petrol","transmission":"automatic","price_min":749000,"price_max":1549000,"mileage_kmpl":18.2,"range_km":null,"seating_capacity":5,"safety_rating":5,"engine_cc":1197,"battery_kwh":null,"power_bhp":128,"image_url":"https://images.unsplash.com/photo-1563720223185-11003d516935?auto=format&fit=crop&w=900&q=80"},
  {"make":"Hyundai","model":"Creta","variant":"SX(O) IVT","body_type":"suv","fuel_type":"petrol","transmission":"automatic","price_min":1100000,"price_max":2000000,"mileage_kmpl":17.4,"range_km":null,"seating_capacity":5,"safety_rating":3,"engine_cc":1497,"battery_kwh":null,"power_bhp":113,"image_url":"https://images.unsplash.com/photo-1511919884226-fd3cad34687c?auto=format&fit=crop&w=900&q=80"},
  {"make":"Kia","model":"Seltos","variant":"GTX Plus DCT","body_type":"suv","fuel_type":"petrol","transmission":"automatic","price_min":1090000,"price_max":2035000,"mileage_kmpl":17.9,"range_km":null,"seating_capacity":5,"safety_rating":3,"engine_cc":1482,"battery_kwh":null,"power_bhp":158,"image_url":"https://images.unsplash.com/photo-1503376780353-7e6692767b70?auto=format&fit=crop&w=900&q=80"},
  {"make":"Honda","model":"Elevate","variant":"ZX CVT","body_type":"suv","fuel_type":"petrol","transmission":"automatic","price_min":1169000,"price_max":1643000,"mileage_kmpl":16.9,"range_km":null,"seating_capacity":5,"safety_rating":4,"engine_cc":1498,"battery_kwh":null,"power_bhp":119,"image_url":"https://images.unsplash.com/photo-1535732820275-9ffd998cac22?auto=format&fit=crop&w=900&q=80"},
  {"make":"Toyota","model":"Urban Cruiser Hyryder","variant":"V Hybrid","body_type":"suv","fuel_type":"hybrid","transmission":"automatic","price_min":1114000,"price_max":1999000,"mileage_kmpl":27.9,"range_km":null,"seating_capacity":5,"safety_rating":4,"engine_cc":1490,"battery_kwh":0.76,"power_bhp":114,"image_url":"https://images.unsplash.com/photo-1532974297617-c0f05fe48bff?auto=format&fit=crop&w=900&q=80"},
  {"make":"Maruti Suzuki","model":"Grand Vitara","variant":"Alpha Plus Hybrid","body_type":"suv","fuel_type":"hybrid","transmission":"automatic","price_min":1087000,"price_max":1997000,"mileage_kmpl":27.9,"range_km":null,"seating_capacity":5,"safety_rating":4,"engine_cc":1490,"battery_kwh":0.76,"power_bhp":114,"image_url":"https://images.unsplash.com/photo-1449965408869-eaa3f722e40d?auto=format&fit=crop&w=900&q=80"},
  {"make":"MG","model":"Comet EV","variant":"Plush","body_type":"hatchback","fuel_type":"electric","transmission":"automatic","price_min":699000,"price_max":953000,"mileage_kmpl":null,"range_km":230,"seating_capacity":4,"safety_rating":3,"engine_cc":null,"battery_kwh":17.3,"power_bhp":41,"image_url":"https://images.unsplash.com/photo-1597007066704-67bf2068d5b2?auto=format&fit=crop&w=900&q=80"},
  {"make":"MG","model":"ZS EV","variant":"Exclusive Pro","body_type":"suv","fuel_type":"electric","transmission":"automatic","price_min":1898000,"price_max":2544000,"mileage_kmpl":null,"range_km":461,"seating_capacity":5,"safety_rating":5,"engine_cc":null,"battery_kwh":50.3,"power_bhp":174,"image_url":"https://images.unsplash.com/photo-1591293836027-e05b48473b67?auto=format&fit=crop&w=900&q=80"},
  {"make":"Mahindra","model":"Scorpio N","variant":"Z8L Diesel AT","body_type":"suv","fuel_type":"diesel","transmission":"automatic","price_min":1360000,"price_max":2454000,"mileage_kmpl":15.4,"range_km":null,"seating_capacity":7,"safety_rating":5,"engine_cc":2198,"battery_kwh":null,"power_bhp":172,"image_url":"https://images.unsplash.com/photo-1504215680853-026ed2a45def?auto=format&fit=crop&w=900&q=80"},
  {"make":"Mahindra","model":"XUV700","variant":"AX7L Diesel AT","body_type":"suv","fuel_type":"diesel","transmission":"automatic","price_min":1399000,"price_max":2699000,"mileage_kmpl":16.6,"range_km":null,"seating_capacity":7,"safety_rating":5,"engine_cc":2198,"battery_kwh":null,"power_bhp":182,"image_url":"https://images.unsplash.com/photo-1523983388277-336a66bf9bcd?auto=format&fit=crop&w=900&q=80"},
  {"make":"Toyota","model":"Innova Hycross","variant":"ZX(O) Hybrid","body_type":"muv","fuel_type":"hybrid","transmission":"automatic","price_min":1900000,"price_max":3050000,"mileage_kmpl":23.2,"range_km":null,"seating_capacity":7,"safety_rating":5,"engine_cc":1987,"battery_kwh":1.6,"power_bhp":183,"image_url":"https://images.unsplash.com/photo-1549317661-bd32c8ce0db2?auto=format&fit=crop&w=900&q=80"},
  {"make":"Maruti Suzuki","model":"Ertiga","variant":"ZXi Plus AT","body_type":"muv","fuel_type":"petrol","transmission":"automatic","price_min":869000,"price_max":1303000,"mileage_kmpl":20.3,"range_km":null,"seating_capacity":7,"safety_rating":3,"engine_cc":1462,"battery_kwh":null,"power_bhp":102,"image_url":"https://images.unsplash.com/photo-1542282088-fe8426682b8f?auto=format&fit=crop&w=900&q=80"},
  {"make":"Kia","model":"Carens","variant":"Luxury Plus DCT","body_type":"muv","fuel_type":"petrol","transmission":"automatic","price_min":1052000,"price_max":1944000,"mileage_kmpl":16.5,"range_km":null,"seating_capacity":7,"safety_rating":3,"engine_cc":1482,"battery_kwh":null,"power_bhp":158,"image_url":"https://images.unsplash.com/photo-1541443131876-44b03de101c5?auto=format&fit=crop&w=900&q=80"},
  {"make":"Honda","model":"City","variant":"ZX CVT","body_type":"sedan","fuel_type":"petrol","transmission":"automatic","price_min":1208000,"price_max":1648000,"mileage_kmpl":18.4,"range_km":null,"seating_capacity":5,"safety_rating":5,"engine_cc":1498,"battery_kwh":null,"power_bhp":119,"image_url":"https://images.unsplash.com/photo-1554744512-d6c603f27c54?auto=format&fit=crop&w=900&q=80"},
  {"make":"Skoda","model":"Slavia","variant":"Style DSG","body_type":"sedan","fuel_type":"petrol","transmission":"automatic","price_min":1139000,"price_max":1899000,"mileage_kmpl":18.7,"range_km":null,"seating_capacity":5,"safety_rating":5,"engine_cc":1498,"battery_kwh":null,"power_bhp":148,"image_url":"https://images.unsplash.com/photo-1494905998402-395d579af36f?auto=format&fit=crop&w=900&q=80"},
  {"make":"Volkswagen","model":"Virtus","variant":"GT Plus DSG","body_type":"sedan","fuel_type":"petrol","transmission":"automatic","price_min":1119000,"price_max":1941000,"mileage_kmpl":18.7,"range_km":null,"seating_capacity":5,"safety_rating":5,"engine_cc":1498,"battery_kwh":null,"power_bhp":148,"image_url":"https://images.unsplash.com/photo-1542362567-b07e54358753?auto=format&fit=crop&w=900&q=80"}
]
